nfdos/__init__.py
nfdos/__main__.py
nfdos/classmodule.py
nfdos/funcmodule.py
neoricalex-0.0.1.dist-info/LICENSE
neoricalex-0.0.1.dist-info/METADATA
neoricalex-0.0.1.dist-info/WHEEL
neoricalex-0.0.1.dist-info/entry_points.txt
neoricalex-0.0.1.dist-info/top_level.txt
neoricalex-0.0.1.dist-info/RECORD
